bizyengine/__init__.py
bizyengine/version.txt
bizyengine/bizy_server/__init__.py
bizyengine/bizy_server/api_client.py
bizyengine/bizy_server/errno.py
bizyengine/bizy_server/error_handler.py
bizyengine/bizy_server/execution.py
bizyengine/bizy_server/profile.py
bizyengine/bizy_server/resp.py
bizyengine/bizy_server/server.py
bizyengine/bizy_server/stream_response.py
bizyengine/bizy_server/utils.py
bizyengine/bizyair_extras/__init__.py
bizyengine/bizyair_extras/nodes_advanced_refluxcontrol.py
bizyengine/bizyair_extras/nodes_cogview4.py
bizyengine/bizyair_extras/nodes_comfyui_detail_daemon.py
bizyengine/bizyair_extras/nodes_comfyui_instantid.py
bizyengine/bizyair_extras/nodes_comfyui_layerstyle_advance.py
bizyengine/bizyair_extras/nodes_comfyui_pulid_flux.py
bizyengine/bizyair_extras/nodes_controlnet.py
bizyengine/bizyair_extras/nodes_custom_sampler.py
bizyengine/bizyair_extras/nodes_dataset.py
bizyengine/bizyair_extras/nodes_differential_diffusion.py
bizyengine/bizyair_extras/nodes_flux.py
bizyengine/bizyair_extras/nodes_hunyuan3d.py
bizyengine/bizyair_extras/nodes_image_utils.py
bizyengine/bizyair_extras/nodes_ip2p.py
bizyengine/bizyair_extras/nodes_janus_pro.py
bizyengine/bizyair_extras/nodes_model_advanced.py
bizyengine/bizyair_extras/nodes_nunchaku.py
bizyengine/bizyair_extras/nodes_reactor.py
bizyengine/bizyair_extras/nodes_sam2.py
bizyengine/bizyair_extras/nodes_sd3.py
bizyengine/bizyair_extras/nodes_segment_anything.py
bizyengine/bizyair_extras/nodes_segment_anything_utils.py
bizyengine/bizyair_extras/nodes_testing_utils.py
bizyengine/bizyair_extras/nodes_trellis.py
bizyengine/bizyair_extras/nodes_ultimatesdupscale.py
bizyengine/bizyair_extras/nodes_upscale_model.py
bizyengine/bizyair_extras/nodes_utils.py
bizyengine/bizyair_extras/nodes_wan_i2v.py
bizyengine/bizyair_extras/nodes_wan_video.py
bizyengine/bizyair_extras/route_bizyair_tools.py
bizyengine/bizyair_extras/nodes_ipadapter_plus/__init__.py
bizyengine-1.2.82.dist-info/METADATA
bizyengine-1.2.82.dist-info/WHEEL
bizyengine-1.2.82.dist-info/top_level.txt
bizyengine-1.2.82.dist-info/RECORD
