Metadata-Version: 2.4
Name: bizyengine
Version: 1.2.82
Summary: [a/BizyAir](https://github.com/siliconflow/BizyAir) Comfy Nodes that can run in any environment.
Author-email: SiliconFlow <yaochi@siliconflow.cn>
Project-URL: Repository, https://github.com/siliconflow/BizyAir
Classifier: Programming Language :: Python :: 3
Classifier: License :: OSI Approved :: MIT License
Classifier: Operating System :: OS Independent
Requires-Python: >=3.10
Requires-Dist: requests
Requires-Dist: inputimeout
Requires-Dist: openai>=1.77.0
Requires-Dist: pycryptodome
Requires-Dist: mcp>=1.18.0
Requires-Dist: bizyairsdk>=0.1.5
